{"assets":[{"id":"el-16-0oCX","layers":[{"ddd":0,"ind":1,"ty":4,"nm":"Layer 1","hd":false,"sr":1,"ks":{"a":{"a":0,"k":[40.962,44.983]},"o":{"a":0,"k":100},"p":{"a":0,"k":[40.962,44.983]},"r":{"a":0,"k":0},"s":{"a":0,"k":[100,100]},"sk":{"a":0,"k":0},"sa":{"a":0,"k":0}},"ao":0,"ip":0,"op":121,"st":0,"bm":0,"shapes":[{"ty":"gr","hd":false,"nm":"Path 1 Group","bm":0,"it":[{"ty":"sh","hd":false,"nm":"Path 1","d":1,"ks":{"a":0,"k":{"c":false,"i":[[0,0],[0.499,0],[0,0.745],[-0.5,0],[0,-0.746]],"o":[[0,0.745],[-0.5,0],[0,-0.745],[0.499,0],[0,0]],"v":[[41.866,44.983],[40.962,46.333],[40.058,44.983],[40.962,43.633],[41.866,44.983]]}}},{"ty":"fl","hd":false,"bm":0,"c":{"a":0,"k":[0,0,0]},"r":1,"o":{"a":0,"k":100}},{"ty":"tr","nm":"Transform","a":{"a":0,"k":[0,0]},"o":{"a":0,"k":100},"p":{"a":0,"k":[0,0]},"r":{"a":0,"k":0},"s":{"a":0,"k":[100,100]},"sk":{"a":0,"k":0},"sa":{"a":0,"k":0}}],"np":0}]},{"ddd":0,"ind":3,"ty":4,"nm":"Layer 2","hd":true,"sr":1,"ks":{"a":{"a":0,"k":[25.792,26.719]},"o":{"a":0,"k":100},"p":{"a":0,"k":[25.792,26.719]},"r":{"a":0,"k":0},"s":{"a":0,"k":[100,100]},"sk":{"a":0,"k":0},"sa":{"a":0,"k":0}},"ao":0,"ip":0,"op":121,"st":0,"bm":0,"shapes":[{"ty":"gr","hd":true,"nm":"Path 1 Group","bm":0,"it":[{"ty":"sh","hd":true,"nm":"Path 1","d":1,"ks":{"a":0,"k":{"c":false,"i":[[0,0],[0.171,-0.145],[2.529,-0.62],[-1.082,0.922]],"o":[[2.463,-2.095],[-0.17,0.145],[-2.107,0.517],[0,0]],"v":[[17.966,28.77],[24.466,32.43],[19.982,31.14],[17.966,28.77]]}}},{"ty":"fl","hd":false,"bm":0,"c":{"a":0,"k":[1,1,1]},"r":1,"o":{"a":0,"k":100}},{"ty":"tr","nm":"Transform","a":{"a":0,"k":[0,0]},"o":{"a":0,"k":100},"p":{"a":0,"k":[0,0]},"r":{"a":0,"k":0},"s":{"a":0,"k":[100,100]},"sk":{"a":0,"k":0},"sa":{"a":0,"k":0}}],"np":0},{"ty":"gr","hd":true,"nm":"Path 1 Group","bm":0,"it":[{"ty":"sh","hd":true,"nm":"Path 1","d":1,"ks":{"a":0,"k":{"c":false,"i":[[0,0],[-0.171,-0.145],[-2.529,-0.62],[1.083,0.922]],"o":[[-2.463,-2.095],[0.17,0.145],[2.107,0.517],[0,0]],"v":[[33.617,26.77],[27.117,30.43],[31.601,29.14],[33.617,26.77]]}}},{"ty":"fl","hd":false,"bm":0,"c":{"a":0,"k":[1,1,1]},"r":1,"o":{"a":0,"k":100}},{"ty":"tr","nm":"Transform","a":{"a":0,"k":[0,0]},"o":{"a":0,"k":100},"p":{"a":0,"k":[0,0]},"r":{"a":0,"k":0},"s":{"a":0,"k":[100,100]},"sk":{"a":0,"k":0},"sa":{"a":0,"k":0}}],"np":0},{"ty":"gr","hd":true,"nm":"Path 1 Group","bm":0,"it":[{"ty":"sh","hd":true,"nm":"Path 1","d":1,"ks":{"a":0,"k":{"c":false,"i":[[0,0],[-0.288,0],[-3,1.5],[1.832,0]],"o":[[-4.169,0],[0.288,0],[2.5,-1.25],[0,0]],"v":[[28.522,21],[25.197,30],[28.522,25],[28.522,21]]}}},{"ty":"fl","hd":false,"bm":0,"c":{"a":0,"k":[1,1,1]},"r":1,"o":{"a":0,"k":100}},{"ty":"tr","nm":"Transform","a":{"a":0,"k":[0,0]},"o":{"a":0,"k":100},"p":{"a":0,"k":[0,0]},"r":{"a":0,"k":0},"s":{"a":0,"k":[100,100]},"sk":{"a":0,"k":0},"sa":{"a":0,"k":0}}],"np":0}]},{"ddd":0,"ind":7,"ty":4,"nm":"Layer 2","hd":false,"sr":1,"ks":{"a":{"a":0,"k":[23.9,37.932]},"o":{"a":0,"k":100},"p":{"a":0,"k":[23.9,37.932]},"r":{"a":0,"k":0},"s":{"a":0,"k":[100,100]},"sk":{"a":0,"k":0},"sa":{"a":0,"k":0}},"ao":0,"ip":0,"op":121,"st":0,"bm":0,"shapes":[{"ty":"gr","hd":false,"nm":"Path 1 Group","bm":0,"it":[{"ty":"sh","hd":false,"nm":"Path 1","d":1,"ks":{"a":1,"k":[{"t":0,"s":[{"c":false,"i":[[0,0],[0.171,-0.145],[2.529,-0.62],[-1.082,0.922]],"o":[[2.463,-2.095],[-0.17,0.145],[-2.107,0.517],[0,0]],"v":[[17.966,28.77],[24.466,32.43],[19.982,31.14],[17.966,28.77]]}],"i":{"x":0.75,"y":0.75},"o":{"x":0.25,"y":0.25}},{"t":120,"s":[{"c":false,"i":[[0,0],[-0.351,-0.39],[1.044,-1.651],[-1.082,0.922]],"o":[[1.48,-0.601],[0.351,0.39],[-2.107,0.517],[0,0]],"v":[[17.966,28.77],[20.232,28.828],[19.982,31.14],[17.966,28.77]]}],"i":{"x":0,"y":0},"o":{"x":1,"y":1}}]}},{"ty":"fl","hd":false,"bm":0,"c":{"a":0,"k":[1,1,1]},"r":1,"o":{"a":0,"k":100}},{"ty":"tr","nm":"Transform","a":{"a":0,"k":[25.291,32.538]},"o":{"a":0,"k":100},"p":{"a":1,"k":[{"t":0,"s":[23.667,38.97],"i":{"x":0.75,"y":0.75},"o":{"x":0.25,"y":0.25},"ti":[13.059366147786236,-5.580925704182153],"to":[-0.12865086865306882,-6.1593538984267875]},{"t":120,"s":[8.244,27.198],"i":{"x":0,"y":0},"o":{"x":1,"y":1}}]},"r":{"a":1,"k":[{"t":0,"s":[45],"i":{"x":0.75,"y":0.75},"o":{"x":0.25,"y":0.25}},{"t":120,"s":[-30],"i":{"x":0,"y":0},"o":{"x":1,"y":1}}]},"s":{"a":1,"k":[{"t":0,"s":[20,20],"i":{"x":0.75,"y":0.75},"o":{"x":0.25,"y":0.25}},{"t":60,"s":[100,100],"i":{"x":0.75,"y":0.75},"o":{"x":0.25,"y":0.25}},{"t":120,"s":[0,0],"i":{"x":0,"y":0},"o":{"x":1,"y":1}}]},"sk":{"a":0,"k":0},"sa":{"a":0,"k":0}}],"np":0},{"ty":"gr","hd":false,"nm":"Path 1 Group","bm":0,"it":[{"ty":"sh","hd":false,"nm":"Path 1","d":1,"ks":{"a":1,"k":[{"t":0,"s":[{"c":false,"i":[[0,0],[-0.171,-0.145],[-2.529,-0.62],[1.083,0.922]],"o":[[-2.463,-2.095],[0.17,0.145],[2.107,0.517],[0,0]],"v":[[33.617,26.77],[27.117,30.43],[31.601,29.14],[33.617,26.77]]}],"i":{"x":0.75,"y":0.75},"o":{"x":0.25,"y":0.25}},{"t":120,"s":[{"c":false,"i":[[0,0],[0.181,-0.584],[-2.163,-0.56],[0.489,0.384]],"o":[[-2.463,-2.095],[-0.181,0.584],[2.163,0.56],[0,0]],"v":[[33.617,26.77],[30.952,27.355],[31.805,29.422],[33.617,26.77]]}],"i":{"x":0,"y":0},"o":{"x":1,"y":1}}]}},{"ty":"fl","hd":false,"bm":0,"c":{"a":0,"k":[1,1,1]},"r":1,"o":{"a":0,"k":100}},{"ty":"tr","nm":"Transform","a":{"a":0,"k":[25.943,30.853]},"o":{"a":0,"k":100},"p":{"a":1,"k":[{"t":0,"s":[23.671,38.965],"i":{"x":0.75,"y":0.75},"o":{"x":0.25,"y":0.25},"ti":[-11.059244701928456,-2.067255145346113],"to":[0.3503773858509692,-6.950738383982281]},{"t":120,"s":[37.074,28.514],"i":{"x":0,"y":0},"o":{"x":1,"y":1}}]},"r":{"a":1,"k":[{"t":0,"s":[-15],"i":{"x":0.75,"y":0.75},"o":{"x":0.25,"y":0.25}},{"t":120,"s":[49],"i":{"x":0,"y":0},"o":{"x":1,"y":1}}]},"s":{"a":1,"k":[{"t":0,"s":[20,20],"i":{"x":0.75,"y":0.75},"o":{"x":0.25,"y":0.25}},{"t":60,"s":[100,100],"i":{"x":0.75,"y":0.75},"o":{"x":0.25,"y":0.25}},{"t":120,"s":[0,0],"i":{"x":0,"y":0},"o":{"x":1,"y":1}}]},"sk":{"a":0,"k":0},"sa":{"a":0,"k":0}}],"np":0},{"ty":"gr","hd":false,"nm":"Path 1 Group","bm":0,"it":[{"ty":"sh","hd":false,"nm":"Path 1","d":1,"ks":{"a":1,"k":[{"t":0,"s":[{"c":false,"i":[[0,0],[-0.288,0],[-3,1.5],[1.832,0]],"o":[[-4.169,0],[0.288,0],[2.5,-1.25],[0,0]],"v":[[28.522,21],[25.197,30],[28.522,25],[28.522,21]]}],"i":{"x":0.75,"y":0.75},"o":{"x":0.25,"y":0.25}},{"t":120,"s":[{"c":false,"i":[[0,0],[-0.394,-0.758],[-0.466,-0.164],[1.832,0]],"o":[[-2.505,-0.069],[0.394,0.758],[2.5,-1.25],[0,0]],"v":[[28.522,21],[27.017,23.931],[28.522,25],[28.522,21]]}],"i":{"x":0,"y":0},"o":{"x":1,"y":1}}]}},{"ty":"fl","hd":false,"bm":0,"c":{"a":0,"k":[1,1,1]},"r":1,"o":{"a":0,"k":100}},{"ty":"tr","nm":"Transform","a":{"a":0,"k":[25.951,30.736]},"o":{"a":0,"k":100},"p":{"a":1,"k":[{"t":0,"s":[23.625,38.973],"i":{"x":0.75,"y":0.75},"o":{"x":0.25,"y":0.25},"ti":[-14.923807905918089,-5.418297009449027],"to":[-0.058322914805663977,-11.642779733560447]},{"t":120,"s":[43.131,22.262],"i":{"x":0,"y":0},"o":{"x":1,"y":1}}]},"r":{"a":1,"k":[{"t":0,"s":[0],"i":{"x":0.75,"y":0.75},"o":{"x":0.25,"y":0.25}},{"t":120,"s":[90],"i":{"x":0,"y":0},"o":{"x":1,"y":1}}]},"s":{"a":1,"k":[{"t":0,"s":[20,20],"i":{"x":0.75,"y":0.75},"o":{"x":0.25,"y":0.25}},{"t":60,"s":[100,100],"i":{"x":0.75,"y":0.75},"o":{"x":0.25,"y":0.25}},{"t":120,"s":[0,0],"i":{"x":0,"y":0},"o":{"x":1,"y":1}}]},"sk":{"a":0,"k":0},"sa":{"a":0,"k":0}}],"np":0}]},{"ddd":0,"ind":11,"ty":4,"nm":"Layer 3","hd":false,"sr":1,"ks":{"a":{"a":0,"k":[38.739,42.974]},"o":{"a":0,"k":100},"p":{"a":0,"k":[38.739,42.974]},"r":{"a":0,"k":0},"s":{"a":0,"k":[100,100]},"sk":{"a":0,"k":0},"sa":{"a":0,"k":0}},"ao":0,"ip":0,"op":121,"st":0,"bm":0,"shapes":[{"ty":"gr","hd":false,"nm":"Path 1 Group","bm":0,"it":[{"ty":"sh","hd":false,"nm":"Path 1","d":1,"ks":{"a":1,"k":[{"t":0,"s":[{"c":false,"i":[[0,0],[-1.764,0],[0,0],[1.84,-0.482],[0.085,-0.023],[0.261,-0.348],[0.006,-0.176],[0.116,-2.601],[0.647,-0.791],[0.131,0.117],[1.82,-0.169],[-0.207,-0.016],[-0.344,-1.439],[0.287,0],[3.732,2.87],[1.597,2.325],[0.735,-0.001],[0,0],[-0.055,0.28],[-1.397,0],[0,0],[-0.46,-0.381],[-3.583,-0.519],[-0.691,0.019],[0.396,0.013],[0,0],[-0.082,1.603],[0.121,0.155],[1.147,0.31],[0,3.742],[-1.989,-0.023],[-0.758,0],[-0.629,-1.251],[-0.116,0.23]],"o":[[0.631,-1.251],[0,0],[0,4.254],[-0.1,0.026],[-1.164,0.312],[-0.106,0.141],[-0.017,0.455],[-0.129,2.916],[-0.113,0.135],[-1.528,-1.34],[-0.21,0.019],[6.573,0.518],[0.062,0.281],[-6.165,0.103],[-3.048,-2.346],[-0.419,-0.604],[0,0],[-0.286,0.003],[0.256,-1.297],[0,0],[0.597,-0.001],[1.777,1.477],[0.93,0.135],[0.396,-0.011],[-0.106,-0.003],[0,0],[0.008,-0.196],[-0.267,-0.35],[-1.65,-0.445],[0,-0.068],[1,0.011],[1.763,0],[0.116,0.23],[0,0]],"v":[[53.742,33.196],[57.754,31.046],[64.479,31],[58.446,36.832],[58.169,36.906],[56.144,38.176],[55.971,38.663],[55.791,42.931],[53.121,49.19],[52.676,49.222],[46.649,48.019],[46.653,48.352],[55.107,54.396],[54.668,54.943],[42.066,50.796],[33.166,39.937],[31.323,38.974],[13.495,38.974],[13.048,38.437],[15.865,36.159],[36.16,36.159],[37.795,36.747],[48.003,42.529],[50.428,42.686],[50.426,42.083],[49.926,42.083],[50.948,38.705],[50.773,38.161],[48.759,36.904],[42.449,31.044],[46.413,31.022],[49.173,31.045],[53.184,33.195],[53.742,33.195]]}],"i":{"x":0.75,"y":0.75},"o":{"x":0.25,"y":0.25}},{"t":60,"s":[{"c":false,"i":[[0,0],[-1.764,0],[0,0],[1.84,-0.482],[0.085,-0.023],[0.261,-0.348],[0.006,-0.176],[0.116,-2.601],[0.647,-0.791],[0.131,0.117],[1.82,-0.169],[-0.207,-0.016],[-0.344,-1.439],[0.287,0],[3.732,2.87],[1.597,2.325],[0.735,-0.001],[0,0],[-0.055,0.28],[-1.397,0],[0,0],[-0.46,-0.381],[-3.583,-0.519],[-0.691,0.019],[0.396,0.013],[0,0],[-0.082,1.603],[0.121,0.155],[1.147,0.31],[0,3.742],[-1.989,-0.023],[-0.758,0],[-0.629,-1.251],[-0.116,0.23]],"o":[[0.631,-1.251],[0,0],[0,4.254],[-0.1,0.026],[-1.164,0.312],[-0.106,0.141],[-0.017,0.455],[-0.129,2.916],[-0.113,0.135],[-1.528,-1.34],[-0.21,0.019],[6.573,0.518],[0.062,0.281],[-6.165,0.103],[-3.048,-2.346],[-0.419,-0.604],[0,0],[-0.286,0.003],[0.256,-1.297],[0,0],[0.597,-0.001],[1.777,1.477],[0.93,0.135],[0.396,-0.011],[-0.106,-0.003],[0,0],[0.008,-0.196],[-0.267,-0.35],[-1.65,-0.445],[0,-0.068],[1,0.011],[1.763,0],[0.116,0.23],[0,0]],"v":[[53.742,33.196],[57.754,31.046],[64.479,31],[58.446,36.832],[58.169,36.906],[56.144,38.176],[55.971,38.663],[55.791,42.931],[53.121,49.19],[52.676,49.222],[47,48],[46.649,48.019],[55.454,54.044],[55.015,54.591],[42.413,50.444],[33.166,39.937],[31.323,38.974],[13.495,38.974],[13.048,38.437],[15.865,36.159],[36.16,36.159],[37.795,36.747],[48.003,42.529],[50.428,42.686],[50.426,42.083],[49.926,42.083],[50.948,38.705],[50.773,38.161],[48.759,36.904],[42.449,31.044],[46.413,31.022],[49.173,31.045],[53.184,33.195],[53.742,33.195]]}],"i":{"x":0.75,"y":0.75},"o":{"x":0.25,"y":0.25}},{"t":120,"s":[{"c":false,"i":[[0,0],[-1.764,0],[0,0],[1.84,-0.482],[0.085,-0.023],[0.261,-0.348],[0.006,-0.176],[0.116,-2.601],[0.647,-0.791],[0.131,0.117],[1.82,-0.169],[-0.207,-0.016],[-0.344,-1.439],[0.287,0],[3.732,2.87],[1.597,2.325],[0.735,-0.001],[0,0],[-0.055,0.28],[-1.397,0],[0,0],[-0.46,-0.381],[-3.583,-0.519],[-0.691,0.019],[0.396,0.013],[0,0],[-0.082,1.603],[0.121,0.155],[1.147,0.31],[0,3.742],[-1.989,-0.023],[-0.758,0],[-0.629,-1.251],[-0.116,0.23]],"o":[[0.631,-1.251],[0,0],[0,4.254],[-0.1,0.026],[-1.164,0.312],[-0.106,0.141],[-0.017,0.455],[-0.129,2.916],[-0.113,0.135],[-1.528,-1.34],[-0.21,0.019],[6.573,0.518],[0.062,0.281],[-6.165,0.103],[-3.048,-2.346],[-0.419,-0.604],[0,0],[-0.286,0.003],[0.256,-1.297],[0,0],[0.597,-0.001],[1.777,1.477],[0.93,0.135],[0.396,-0.011],[-0.106,-0.003],[0,0],[0.008,-0.196],[-0.267,-0.35],[-1.65,-0.445],[0,-0.068],[1,0.011],[1.763,0],[0.116,0.23],[0,0]],"v":[[53.742,33.196],[57.754,31.046],[64.479,31],[58.446,36.832],[58.169,36.906],[56.144,38.176],[55.971,38.663],[55.791,42.931],[53.121,49.19],[52.676,49.222],[46.649,48.019],[46.653,48.352],[55.107,54.396],[54.668,54.943],[42.066,50.796],[33.166,39.937],[31.323,38.974],[13.495,38.974],[13.048,38.437],[15.865,36.159],[36.16,36.159],[37.795,36.747],[48.003,42.529],[50.428,42.686],[50.426,42.083],[49.926,42.083],[50.948,38.705],[50.773,38.161],[48.759,36.904],[42.449,31.044],[46.413,31.022],[49.173,31.045],[53.184,33.195],[53.742,33.195]]}],"i":{"x":0,"y":0},"o":{"x":1,"y":1}}]}},{"ty":"fl","hd":false,"bm":0,"c":{"a":0,"k":[1,1,1]},"r":1,"o":{"a":0,"k":100}},{"ty":"tr","nm":"Transform","a":{"a":0,"k":[0,0]},"o":{"a":0,"k":100},"p":{"a":0,"k":[0,0]},"r":{"a":0,"k":0},"s":{"a":0,"k":[100,100]},"sk":{"a":0,"k":0},"sa":{"a":0,"k":0}}],"np":0},{"ty":"gr","hd":false,"nm":"Path 1 (5) Group","bm":0,"it":[{"ty":"sh","hd":false,"nm":"Path 1 (5)","d":1,"ks":{"a":0,"k":{"c":false,"i":[[0,0],[0,0],[-0.634,-0.739],[0,0],[2.229,3.03],[0,0],[0,0],[0,0],[-3.807,0]],"o":[[0,0],[0.6,0.768],[0,0],[-3.808,0],[0,0],[0,0],[0,0],[2.229,3.028],[0,0]],"v":[[34.412,46.122],[35.79,46.122],[37.654,48.406],[32.78,48.406],[23.167,43.583],[20.762,40.313],[24.074,40.313],[24.799,41.299],[34.411,46.122]]}}},{"ty":"sh","hd":false,"nm":"Path 1 (5)","d":1,"ks":{"a":0,"k":{"c":true,"i":[[0,0],[1.309,1.765],[0,0],[0,0],[0,0],[-3.808,0],[0,0],[0.557,0.77]],"o":[[-2.198,0.006],[0,0],[0,0],[0,0],[2.228,3.03],[0,0],[-0.58,-0.753],[0,0]],"v":[[33.771,43.437],[28.194,40.639],[27.954,40.313],[24.643,40.313],[25.073,40.897],[34.685,45.721],[35.478,45.721],[33.773,43.437]]}}},{"ty":"sh","hd":false,"nm":"Path 1 (5)","d":1,"ks":{"a":0,"k":{"c":false,"i":[[0,0],[0.615,0.087],[0,0],[0,0],[-1.847,0.004],[0.412,0.599]],"o":[[-0.354,-0.511],[0,0],[0,0],[1.1,1.483],[-0.424,-0.591],[0,0]],"v":[[32.228,41.251],[30.708,40.313],[28.522,40.313],[28.795,40.683],[33.481,43.036],[32.228,41.251]]}}},{"ty":"sh","hd":false,"nm":"Path 1 (5)","d":1,"ks":{"a":0,"k":{"c":false,"i":[[0,0],[0,0],[2.229,3.028],[0,0],[0,0],[0,0],[-3.807,0],[0,0],[0.749,0.851]],"o":[[0,0],[-3.807,0],[0,0],[0,0],[0,0],[2.23,3.03],[0,0],[-0.71,-0.646],[0,0]],"v":[[38,48.806],[32.504,48.806],[22.891,43.983],[20.191,40.313],[16.88,40.313],[21.26,46.266],[30.873,51.09],[40.209,51.09],[38,48.806]]}}},{"ty":"sh","hd":false,"nm":"Path 1 (5)","d":1,"ks":{"a":0,"k":{"c":true,"i":[[0,0],[-0.132,-0.103],[-0.902,-0.567],[0,0],[2.228,3.03],[0,0],[0,0],[0,0],[-3.808,0]],"o":[[0.137,0.115],[0.956,0.734],[0,0],[-3.807,0],[0,0],[0,0],[0,0],[2.23,3.029],[0,0]],"v":[[40.669,51.492],[41.072,51.819],[43.82,53.775],[28.969,53.775],[19.357,48.952],[13,40.312],[16.312,40.312],[20.988,46.668],[30.601,51.492]]}}},{"ty":"gf","hd":false,"bm":0,"e":{"a":0,"k":[43.835534680206344,54.32113554047402]},"g":{"p":2,"k":{"a":0,"k":[0.3,1,1,1,1,1,1,1,0.3,1,1,0]}},"t":1,"a":{"a":0,"k":0},"h":{"a":0,"k":0},"o":{"a":0,"k":100},"r":1,"s":{"a":0,"k":[42.00000010089832,37.49999991721584]}},{"ty":"tr","nm":"Transform","a":{"a":0,"k":[0,0]},"o":{"a":0,"k":100},"p":{"a":0,"k":[0,0]},"r":{"a":0,"k":0},"s":{"a":0,"k":[100,100]},"sk":{"a":0,"k":0},"sa":{"a":0,"k":0}}],"np":0},{"ty":"gr","hd":false,"nm":"Path 1 Group","bm":0,"it":[{"ty":"sh","hd":false,"nm":"Path 1","d":1,"ks":{"a":0,"k":{"c":false,"i":[[0,0],[0.081,0.075],[0.002,0.002],[1.084,1.426],[0.121,-0.151],[0.837,-1.449],[-0.111,-0.015],[-0.008,0],[-1.11,-0.122],[-1.315,0.202],[-0.492,0.156]],"o":[[0.106,-0.033],[-0.002,-0.002],[-1.371,-1.153],[-0.119,-0.153],[-1.208,1.158],[-0.069,0.089],[0.008,0.001],[0,0],[1.25,0.137],[0.51,-0.078],[0,0]],"v":[[21.603,53.012],[21.659,52.769],[21.652,52.763],[17.957,48.883],[17.486,48.879],[14.403,52.809],[14.499,53.043],[14.523,53.044],[16.462,53.329],[20.099,53.364],[21.603,53.012]]}}},{"ty":"fl","hd":false,"bm":0,"c":{"a":0,"k":[1,1,1]},"r":1,"o":{"a":0,"k":100}},{"ty":"tr","nm":"Transform","a":{"a":0,"k":[27.34,47.392]},"o":{"a":0,"k":100},"p":{"a":1,"k":[{"t":0,"s":[27.34,47.392],"i":{"x":0.75,"y":0.75},"o":{"x":0.25,"y":0.25}},{"t":60,"s":[27.069,47.272],"i":{"x":0.75,"y":0.75},"o":{"x":0.25,"y":0.25},"ti":[0,0],"to":[0,0]},{"t":120,"s":[27.338,47.394],"i":{"x":0,"y":0},"o":{"x":1,"y":1}}]},"r":{"a":1,"k":[{"t":0,"s":[0],"i":{"x":0.75,"y":0.75},"o":{"x":0.25,"y":0.25}},{"t":60,"s":[2],"i":{"x":0.75,"y":0.75},"o":{"x":0.25,"y":0.25}},{"t":120,"s":[0],"i":{"x":0,"y":0},"o":{"x":1,"y":1}}]},"s":{"a":0,"k":[100,100]},"sk":{"a":0,"k":0},"sa":{"a":0,"k":0}}],"np":0}]}]}],"ddd":0,"fr":60,"h":78,"ip":0,"layers":[{"ddd":0,"ind":15,"ty":0,"nm":"Import from Figma","hd":false,"sr":1,"ks":{"a":{"a":0,"k":[39,39]},"o":{"a":0,"k":100},"p":{"a":0,"k":[39,39]},"r":{"a":0,"k":0},"s":{"a":0,"k":[100,100]},"sk":{"a":0,"k":0},"sa":{"a":0,"k":0}},"ao":0,"ip":0,"op":121,"st":0,"bm":0,"h":78,"refId":"el-16-0oCX","w":78}],"meta":{"g":"@phase-software/lottie-exporter 0.7.0"},"nm":"","op":120,"v":"5.6.0","w":78}